Workbook

Sheet Raw_Data
A1: Order_ID | B1: Month | C1: Month_No | D1: Date | E1: City | F1: Category | G1: Product | H1: Channel | I1: Units_Sold | J1: Unit_Price | K1: Revenue | L1: Discount_% | M1: Net_Revenue | N1: Delivery_Days | O1: Order_Status | P1: Payment_Mode | Q1: Return_Reason | R1: Target_Revenue
A2: ORD1001 | B2: Jan | C2: 1 | D2: 2024-01-03 | E2: Hyderabad | F2: Electronics | G2: Smartphone | H2: Website | I2: 4 | J2: 799 | K2: 3196 | L2: 0 | M2: 3196 | N2: 9 | O2: Delivered | P2: COD | R2: 2700
A3: ORD1002 | B3: Feb | C3: 2 | D3: 2024-02-28 | E3: Mumbai | F3: Clothing | G3: Jeans | H3: Marketplace | I3: 4 | J3: 24999 | K3: 99996 | L3: 20 | M3: 79996.8 | N3: 7 | O3: Delivered | P3: Net Banking | R3: 74700
A4: ORD1003 | B4: Mar | C4: 3 | D4: 2024-03-28 | E4: Kolkata | F4: Electronics | G4: Laptop | H4: Mobile App | I4: 5 | J4: 799 | K4: 3995 | L4: 5 | M4: 3795.25 | N4: 6 | O4: Delivered | P4: COD | R4: 3300
A5: ORD1004 | B5: Apr | C5: 4 | D5: 2024-04-10 | E5: Hyderabad | F5: Home & Kitchen | G5: LED Bulb | H5: Website | I5: 12 | J5: 4999 | K5: 59988 | L5: 20 | M5: 47990.4 | N5: 2 | O5: Pending | P5: COD | R5: 41900
A6: ORD1005 | B6: May | C6: 5 | D6: 2024-05-13 | E6: Chennai | F6: Books | G6: Textbook | H6: Marketplace | I6: 2 | J6: 299 | K6: 598 | L6: 5 | M6: 568.1 | N6: 5 | O6: Pending | P6: Credit Card | R6: 600
A7: ORD1006 | B7: Jun | C7: 6 | D7: 2024-06-18 | E7: Pune | F7: Home & Kitchen | G7: Iron | H7: Website | I7: 6 | J7: 1999 | K7: 11994 | L7: 5 | M7: 11394.3 | N7: 5 | O7: Returned | P7: UPI | Q7: Late Delivery | R7: 11900
A8: ORD1007 | B8: Jul | C8: 7 | D8: 2024-07-02 | E8: Ahmedabad | F8: Clothing | G8: Jeans | H8: Mobile App | I8: 5 | J8: 24999 | K8: 124995 | L8: 20 | M8: 99996 | N8: 4 | O8: Delivered | P8: UPI | R8: 91900
A9: ORD1008 | B9: Aug | C9: 8 | D9: 2024-08-21 | E9: Hyderabad | F9: Home & Kitchen | G9: Iron | H9: Website | I9: 4 | J9: 12999 | K9: 51996 | L9: 10 | M9: 46796.4 | N9: 4 | O9: Delivered | P9: COD | R9: 52200
A10: ORD1009 | B10: Sep | C10: 9 | D10: 2024-09-08 | E10: Hyderabad | F10: Sports | G10: Yoga Mat | H10: Website | I10: 4 | J10: 7999 | K10: 31996 | L10: 20 | M10: 25596.8 | N10: 5 | O10: Returned | P10: COD | Q10: Late Delivery | R10: 24800
A11: ORD1010 | B11: Oct | C11: 10 | D11: 2024-10-13 | E11: Ahmedabad | F11: Clothing | G11: Kurta | H11: Website | I11: 13 | J11: 299 | K11: 3887 | L11: 0 | M11: 3887 | N11: 3 | O11: Delivered | P11: COD | R11: 4000
A12: ORD1011 | B12: Nov | C12: 11 | D12: 2024-11-25 | E12: Ahmedabad | F12: Sports | G12: Cycling Gloves | H12: Marketplace | I12: 5 | J12: 7999 | K12: 39995 | L12: 0 | M12: 39995 | N12: 2 | O12: Delivered | P12: Net Banking | R12: 43000
A13: ORD1012 | B13: Dec | C13: 12 | D13: 2024-12-04 | E13: Hyderabad | F13: Home & Kitchen | G13: Mixer | H13: Mobile App | I13: 3 | J13: 4999 | K13: 14997 | L13: 0 | M13: 14997 | N13: 5 | O13: Pending | P13: Credit Card | R13: 15000
A14: ORD1013 | B14: Jan | C14: 1 | D14: 2024-01-01 | E14: Chennai | F14: Home & Kitchen | G14: LED Bulb | H14: Website | I14: 6 | J14: 799 | K14: 4794 | L14: 20 | M14: 3835.2 | N14: 9 | O14: Cancelled | P14: Net Banking | R14: 3600
A15: ORD1014 | B15: Feb | C15: 2 | D15: 2024-02-25 | E15: Hyderabad | F15: Electronics | G15: Earbuds | H15: Website | I15: 1 | J15: 999 | K15: 999 | L15: 20 | M15: 799.2 | N15: 2 | O15: Delivered | P15: COD | R15: 900
A16: ORD1015 | B16: Mar | C16: 3 | D16: 2024-03-07 | E16: Bangalore | F16: Books | G16: Self-Help | H16: Marketplace | I16: 8 | J16: 7999 | K16: 63992 | L16: 5 | M16: 60792.4 | N16: 5 | O16: Delivered | P16: Net Banking | R16: 59400
A17: ORD1016 | B17: Apr | C17: 4 | D17: 2024-04-08 | E17: Hyderabad | F17: Books | G17: Self-Help | H17: Mobile App | I17: 11 | J17: 24999 | K17: 274989 | L17: 10 | M17: 247490.1 | N17: 8 | O17: Cancelled | P17: COD | R17: 219400
A18: ORD1017 | B18: May | C18: 5 | D18: 2024-05-02 | E18: Mumbai | F18: Electronics | G18: Earbuds | H18: Marketplace | I18: 9 | J18: 999 | K18: 8991 | L18: 20 | M18: 7192.8 | N18: 4 | O18: Delivered | P18: UPI | R18: 6600
A19: ORD1018 | B19: Jun | C19: 6 | D19: 2024-06-08 | E19: Chennai | F19: Home & Kitchen | G19: Mixer | H19: Mobile App | I19: 11 | J19: 4999 | K19: 54989 | L19: 5 | M19: 52239.55 | N19: 9 | O19: Delivered | P19: Net Banking | R19: 53400
A20: ORD1019 | B20: Jul | C20: 7 | D20: 2024-07-02 | E20: Chennai | F20: Sports | G20: Football | H20: Website | I20: 2 | J20: 24999 | K20: 49998 | L20: 15 | M20: 42498.3 | N20: 6 | O20: Delivered | P20: COD | R20: 47100
A21: ORD1020 | B21: Aug | C21: 8 | D21: 2024-08-06 | E21: Kolkata | F21: Electronics | G21: Smartphone | H21: Marketplace | I21: 6 | J21: 499 | K21: 2994 | L21: 5 | M21: 2844.3 | N21: 4 | O21: Delivered | P21: COD | R21: 2500
A22: ORD1021 | B22: Sep | C22: 9 | D22: 2024-09-03 | E22: Chennai | F22: Home & Kitchen | G22: Iron | H22: Website | I22: 8 | J22: 7999 | K22: 63992 | L22: 0 | M22: 63992 | N22: 1 | O22: Delivered | P22: Net Banking | R22: 70400
... A34: ORD1033 | B34: Sep | C34: 9 | D34: 2024-09-26 | E34: Mumbai | F34: Clothing | G34: Kurta | H34: Mobile App | I34: 10 | J34: 7999 | K34: 79990 | L34: 5 | M34: 75990.5 | N34: 7 | O34: Delivered | P34: Debit Card | R34: 72900
A35: ORD1034 | B35: Oct | C35: 10 | D35: 2024-10-08 | E35: Chennai | F35: Electronics | G35: Earbuds | H35: Marketplace | I35: 4 | J35: 24999 | K35: 99996 | L35: 0 | M35: 99996 | N35: 6 | O35: Returned | P35: COD | Q35: Late Delivery | R35: 107500
A36: ORD1035 | B36: Nov | C36: 11 | D36: 2024-11-02 | E36: Kolkata | F36: Clothing | G36: Jeans | H36: Website | I36: 3 | J36: 1999 | K36: 5997 | L36: 15 | M36: 5097.45 | N36: 4 | O36: Delivered | P36: UPI | R36: 4900
A37: ORD1036 | B37: Dec | C37: 12 | D37: 2024-12-09 | E37: Chennai | F37: Sports | G37: Yoga Mat | H37: Mobile App | I37: 6 | J37: 1499 | K37: 8994 | L37: 5 | M37: 8544.3 | N37: 4 | O37: Delivered | P37: Credit Card | R37: 8300
A38: ORD1037 | B38: Jan | C38: 1 | D38: 2024-01-09 | E38: Pune | F38: Electronics | G38: Earbuds | H38: Marketplace | I38: 9 | J38: 2999 | K38: 26991 | L38: 20 | M38: 21592.8 | N38: 6 | O38: Pending | P38: UPI | R38: 24000
A39: ORD1038 | B39: Feb | C39: 2 | D39: 2024-02-17 | E39: Hyderabad | F39: Clothing | G39: Kurta | H39: Website | I39: 2 | J39: 12999 | K39: 25998 | L39: 15 | M39: 22098.3 | N39: 6 | O39: Returned | P39: Debit Card | Q39: Damaged | R39: 22800
A40: ORD1039 | B40: Mar | C40: 3 | D40: 2024-03-24 | E40: Chennai | F40: Electronics | G40: Smartwatch | H40: Mobile App | I40: 1 | J40: 2999 | K40: 2999 | L40: 0 | M40: 2999 | N40: 9 | O40: Pending | P40: Net Banking | R40: 3200
A41: ORD1040 | B41: Apr | C41: 4 | D41: 2024-04-10 | E41: Kolkata | F41: Clothing | G41: Saree | H41: Website | I41: 11 | J41: 1999 | K41: 21989 | L41: 20 | M41: 17591.2 | N41: 6 | O41: Delivered | P41: UPI | R41: 18800
A42: ORD1041 | B42: May | C42: 5 | D42: 2024-05-06 | E42: Kolkata | F42: Books | G42: Textbook | H42: Mobile App | I42: 7 | J42: 1499 | K42: 10493 | L42: 20 | M42: 8394.4 | N42: 3 | O42: Delivered | P42: COD | R42: 8800
A43: ORD1042 | B43: Jun | C43: 6 | D43: 2024-06-11 | E43: Hyderabad | F43: Books | G43: Biography | H43: Mobile App | I43: 9 | J43: 299 | K43: 2691 | L43: 10 | M43: 2421.9 | N43: 5 | O43: Delivered | P43: Net Banking | R43: 2500
A44: ORD1043 | B44: Jul | C44: 7 | D44: 2024-07-21 | E44: Ahmedabad | F44: Sports | G44: Football | H44: Marketplace | I44: 4 | J44: 7999 | K44: 31996 | L44: 15 | M44: 27196.6 | N44: 3 | O44: Delivered | P44: Debit Card | R44: 27300
A45: ORD1044 | B45: Aug | C45: 8 | D45: 2024-08-16 | E45: Delhi | F45: Books | G45: Textbook | H45: Website | I45: 11 | J45: 1499 | K45: 16489 | L45: 5 | M45: 15664.55 | N45: 4 | O45: Delivered | P45: UPI | R45: 14500
A46: ORD1045 | B46: Sep | C46: 9 | D46: 2024-09-05 | E46: Ahmedabad | F46: Books | G46: Fiction Novel | H46: Mobile App | I46: 15 | J46: 24999 | K46: 374985 | L46: 20 | M46: 299988 | N46: 4 | O46: Returned | P46: COD | Q46: Damaged | R46: 291000
A47: ORD1046 | B47: Oct | C47: 10 | D47: 2024-10-26 | E47: Kolkata | F47: Electronics | G47: Smartphone | H47: Website | I47: 3 | J47: 7999 | K47: 23997 | L47: 15 | M47: 20397.45 | N47: 1 | O47: Delivered | P47: UPI | R47: 20100
A48: ORD1047 | B48: Nov | C48: 11 | D48: 2024-11-16 | E48: Pune | F48: Sports | G48: Cycling Gloves | H48: Mobile App | I48: 10 | J48: 7999 | K48: 79990 | L48: 15 | M48: 67991.5 | N48: 9 | O48: Delivered | P48: Credit Card | R48: 73000
A49: ORD1048 | B49: Dec | C49: 12 | D49: 2024-12-08 | E49: Chennai | F49: Sports | G49: Badminton Racket | H49: Marketplace | I49: 5 | J49: 7999 | K49: 39995 | L49: 15 | M49: 33995.75 | N49: 4 | O49: Delivered | P49: UPI | R49: 36200
A50: ORD1049 | B50: Jan | C50: 1 | D50: 2024-01-03 | E50: Pune | F50: Home & Kitchen | G50: Water Purifier | H50: Marketplace | I50: 2 | J50: 799 | K50: 1598 | L50: 5 | M50: 1518.1 | N50: 4 | O50: Delivered | P50: Credit Card | R50: 1600
A51: ORD1050 | B51: Feb | C51: 2 | D51: 2024-02-19 | E51: Pune | F51: Sports | G51: Football | H51: Marketplace | I51: 8 | J51: 2999 | K51: 23992 | L51: 0 | M51: 23992 | N51: 4 | O51: Cancelled | P51: COD | R51: 26900
A52: ORD1051 | B52: Mar | C52: 3 | D52: 2024-03-24 | E52: Kolkata | F52: Electronics | G52: Tablet | H52: Mobile App | I52: 1 | J52: 1999 | K52: 1999 | L52: 10 | M52: 1799.1 | N52: 7 | O52: Cancelled | P52: COD | R52: 1800
A53: ORD1052 | B53: Apr | C53: 4 | D53: 2024-04-26 | E53: Chennai | F53: Books | G53: Biography | H53: Mobile App | I53: 4 | J53: 1499 | K53: 5996 | L53: 15 | M53: 5096.6 | N53: 8 | O53: Delivered | P53: Debit Card | R53: 5400
A54: ORD1053 | B54: May | C54: 5 | D54: 2024-05-14 | E54: Ahmedabad | F54: Sports | G54: Yoga Mat | H54: Website | I54: 10 | J54: 7999 | K54: 79990 | L54: 0 | M54: 79990 | N54: 7 | O54: Delivered | P54: UPI | R54: 70000
A55: ORD1054 | B55: Jun | C55: 6 | D55: 2024-06-13 | E55: Bangalore | F55: Clothing | G55: Jacket | H55: Website | I55: 5 | J55: 2999 | K55: 14995 | L55: 10 | M55: 13495.5 | N55: 4 | O55: Delivered | P55: Debit Card | R55: 14600
A56: ORD1055 | B56: Jul | C56: 7 | D56: 2024-07-03 | E56: Hyderabad | F56: Home & Kitchen | G56: Iron | H56: Website | I56: 8 | J56: 299 | K56: 2392 | L56: 20 | M56: 1913.6 | N56: 1 | O56: Pending | P56: Debit Card | R56: 1800
A57: ORD1056 | B57: Aug | C57: 8 | D57: 2024-08-19 | E57: Chennai | F57: Electronics | G57: Smartphone | H57: Website | I57: 14 | J57: 299 | K57: 4186 | L57: 20 | M57: 3348.8 | N57: 3 | O57: Delivered | P57: COD | R57: 3500
A58: ORD1057 | B58: Sep | C58: 9 | D58: 2024-09-01 | E58: Hyderabad | F58: Clothing | G58: Jacket | H58: Mobile App | I58: 3 | J58: 12999 | K58: 38997 | L58: 20 | M58: 31197.6 | N58: 2 | O58: Returned | P58: Credit Card | Q58: Changed Mind | R58: 27500
A59: ORD1058 | B59: Oct | C59: 10 | D59: 2024-10-25 | E59: Kolkata | F59: Home & Kitchen | G59: LED Bulb | H59: Mobile App | I59: 12 | J59: 999 | K59: 11988 | L59: 0 | M59: 11988 | N59: 10 | O59: Delivered | P59: Credit Card | R59: 10600
A60: ORD1059 | B60: Nov | C60: 11 | D60: 2024-11-21 | E60: Delhi | F60: Home & Kitchen | G60: LED Bulb | H60: Marketplace | I60: 13 | J60: 299 | K60: 3887 | L60: 10 | M60: 3498.3 | N60: 9 | O60: Delivered | P60: Debit Card | R60: 3000
A61: ORD1060 | B61: Dec | C61: 12 | D61: 2024-12-21 | E61: Kolkata | F61: Home & Kitchen | G61: Mixer | H61: Mobile App | I61: 2 | J61: 2999 | K61: 5998 | L61: 10 | M61: 5398.2 | N61: 8 | O61: Returned | P61: COD | Q61: Wrong Item | R61: 5800
A62: ORD1061 | B62: Jan | C62: 1 | D62: 2024-01-15 | E62: Ahmedabad | F62: Home & Kitchen | G62: LED Bulb | H62: Mobile App | I62: 7 | J62: 12999 | K62: 90993 | L62: 10 | M62: 81893.7 | N62: 6 | O62: Cancelled | P62: UPI | R62: 76500
A63: ORD1062 | B63: Feb | C63: 2 | D63: 2024-02-11 | E63: Kolkata | F63: Clothing | G63: Jacket | H63: Mobile App | I63: 1 | J63: 4999 | K63: 4999 | L63: 10 | M63: 4499.1 | N63: 3 | O63: Delivered | P63: Debit Card | R63: 4900
A64: ORD1063 | B64: Mar | C64: 3 | D64: 2024-03-25 | E64: Hyderabad | F64: Home & Kitchen | G64: LED Bulb | H64: Marketplace | I64: 1 | J64: 7999 | K64: 7999 | L64: 5 | M64: 7599.05 | N64: 2 | O64: Delivered | P64: COD | R64: 7600
A65: ORD1064 | B65: Apr | C65: 4 | D65: 2024-04-19 | E65: Ahmedabad | F65: Clothing | G65: Jacket | H65: Mobile App | I65: 13 | J65: 299 | K65: 3887 | L65: 0 | M65: 3887 | N65: 5 | O65: Delivered | P65: Credit Card | R65: 3700
A66: ORD1065 | B66: May | C66: 5 | D66: 2024-05-04 | E66: Pune | F66: Home & Kitchen | G66: Iron | H66: Mobile App | I66: 12 | J66: 7999 | K66: 95988 | L66: 10 | M66: 86389.2 | N66: 6 | O66: Returned | P66: Debit Card | Q66: Changed Mind | R66: 79900
A67: ORD1066 | B67: Jun | C67: 6 | D67: 2024-06-25 | E67: Delhi | F67: Clothing | G67: Saree | H67: Marketplace | I67: 9 | J67: 799 | K67: 7191 | L67: 5 | M67: 6831.45 | N67: 4 | O67: Returned | P67: Debit Card | R67: 7000
A68: ORD1067 | B68: Jul | C68: 7 | D68: 2024-07-18 | E68: Hyderabad | F68: Books | G68: Biography | H68: Website | I68: 14 | J68: 999 | K68: 13986 | L68: 10 | M68: 12587.4 | N68: 4 | O68: Delivered | P68: Debit Card | R68: 10800
A69: ORD1068 | B69: Aug | C69: 8 | D69: 2024-08-16 | E69: Mumbai | F69: Clothing | G69: Saree | H69: Website | I69: 9 | J69: 1499 | K69: 13491 | L69: 5 | M69: 12816.45 | N69: 8 | O69: Delivered | P69: UPI | R69: 13100
A70: ORD1069 | B70: Sep | C70: 9 | D70: 2024-09-19 | E70: Pune | F70: Sports | G70: Football | H70: Website | I70: 1 | J70: 1499 | K70: 1499 | L70: 15 | M70: 1274.15 | N70: 2 | O70: Cancelled | P70: COD | R70: 1300
A71: ORD1070 | B71: Oct | C71: 10 | D71: 2024-10-26 | E71: Bangalore | F71: Electronics | G71: Laptop | H71: Marketplace | I71: 5 | J71: 499 | K71: 2495 | L71: 5 | M71: 2370.25 | N71: 2 | O71: Delivered | P71: COD | R71: 2400
A72: ORD1071 | B72: Nov | C72: 11 | D72: 2024-11-02 | E72: Kolkata | F72: Books | G72: Self-Help | H72: Mobile App | I72: 15 | J72: 4999 | K72: 74985 | L72: 10 | M72: 67486.5 | N72: 10 | O72: Pending | P72: Debit Card | R72: 68900
A73: ORD1072 | B73: Dec | C73: 12 | D73: 2024-12-01 | E73: Chennai | F73: Books | G73: Fiction Novel | H73: Marketplace | I73: 4 | J73: 1499 | K73: 5996 | L73: 0 | M73: 5996 | N73: 3 | O73: Delivered | P73: Net Banking | R73: 5200
A74: ORD1073 | B74: Jan | C74: 1 | D74: 2024-01-09 | E74: Ahmedabad | F74: Sports | G74: Football | H74: Mobile App | I74: 1 | J74: 999 | K74: 999 | L74: 10 | M74: 899.1 | N74: 5 | O74: Returned | P74: COD | Q74: Quality Issue | R74: 900
A75: ORD1074 | B75: Feb | C75: 2 | D75: 2024-02-26 | E75: Kolkata | F75: Books | G75: Self-Help | H75: Website | I75: 9 | J75: 999 | K75: 8991 | L75: 5 | M75: 8541.45 | N75: 5 | O75: Cancelled | P75: UPI | R75: 7400
A76: ORD1075 | B76: Mar | C76: 3 | D76: 2024-03-15 | E76: Hyderabad | F76: Home & Kitchen | G76: LED Bulb | H76: Mobile App | I76: 2 | J76: 4999 | K76: 9998 | L76: 10 | M76: 8998.2 | N76: 7 | O76: Pending | P76: Net Banking | R76: 9100
A77: ORD1076 | B77: Apr | C77: 4 | D77: 2024-04-27 | E77: Mumbai | F77: Electronics | G77: Tablet | H77: Mobile App | I77: 12 | J77: 1999 | K77: 23988 | L77: 20 | M77: 19190.4 | N77: 5 | O77: Delivered | P77: Credit Card | R77: 21800
A78: ORD1077 | B78: May | C78: 5 | D78: 2024-05-15 | E78: Mumbai | F78: Books | G78: Biography | H78: Marketplace | I78: 14 | J78: 1499 | K78: 20986 | L78: 20 | M78: 16788.8 | N78: 1 | O78: Returned | P78: Credit Card | Q78: Damaged | R78: 16900
A79: ORD1078 | B79: Jun | C79: 6 | D79: 2024-06-04 | E79: Kolkata | F79: Home & Kitchen | G79: Pressure Cooker | H79: Marketplace | I79: 14 | J79: 4999 | K79: 69986 | L79: 0 | M79: 69986 | N79: 8 | O79: Delivered | P79: Debit Card | R79: 66200
A80: ORD1079 | B80: Jul | C80: 7 | D80: 2024-07-11 | E80: Kolkata | F80: Clothing | G80: Saree | H80: Marketplace | I80: 8 | J80: 1499 | K80: 11992 | L80: 15 | M80: 10193.2 | N80: 9 | O80: Delivered | P80: UPI | R80: 9600
A81: ORD1080 | B81: Aug | C81: 8 | D81: 2024-08-25 | E81: Mumbai | F81: Electronics | G81: Smartwatch | H81: Marketplace | I81: 14 | J81: 7999 | K81: 111986 | L81: 15 | M81: 95188.1 | N81: 7 | O81: Delivered | P81: Net Banking | R81: 91200
A82: ORD1081 | B82: Sep | C82: 9 | D82: 2024-09-21 | E82: Mumbai | F82: Sports | G82: Football | H82: Website | I82: 5 | J82: 7999 | K82: 39995 | L82: 5 | M82: 37995.25 | N82: 5 | O82: Delivered | P82: COD | R82: 33700
A83: ORD1082 | B83: Oct | C83: 10 | D83: 2024-10-04 | E83: Bangalore | F83: Books | G83: Self-Help | H83: Mobile App | I83: 9 | J83: 299 | K83: 2691 | L83: 20 | M83: 2152.8 | N83: 7 | O83: Delivered | P83: UPI | R83: 2100
A84: ORD1083 | B84: Nov | C84: 11 | D84: 2024-11-05 | E84: Hyderabad | F84: Clothing | G84: Jacket | H84: Marketplace | I84: 12 | J84: 1499 | K84: 17988 | L84: 15 | M84: 15289.8 | N84: 8 | O84: Pending | P84: Credit Card | R84: 15100
A85: ORD1084 | B85: Dec | C85: 12 | D85: 2024-12-10 | E85: Bangalore | F85: Sports | G85: Yoga Mat | H85: Website | I85: 5 | J85: 2999 | K85: 14995 | L85: 10 | M85: 13495.5 | N85: 9 | O85: Delivered | P85: UPI | R85: 12600
A86: ORD1085 | B86: Jan | C86: 1 | D86: 2024-01-11 | E86: Ahmedabad | F86: Books | G86: Biography | H86: Website | I86: 8 | J86: 7999 | K86: 63992 | L86: 15 | M86: 54393.2 | N86: 6 | O86: Delivered | P86: Net Banking | R86: 52400
A87: ORD1086 | B87: Feb | C87: 2 | D87: 2024-02-26 | E87: Kolkata | F87: Clothing | G87: Jeans | H87: Website | I87: 14 | J87: 2999 | K87: 41986 | L87: 0 | M87: 41986 | N87: 6 | O87: Returned | P87: COD | Q87: Damaged | R87: 48100
A88: ORD1087 | B88: Mar | C88: 3 | D88: 2024-03-15 | E88: Mumbai | F88: Clothing | G88: Jacket | H88: Website | I88: 9 | J88: 12999 | K88: 116991 | L88: 10 | M88: 105291.9 | N88: 2 | O88: Cancelled | P88: COD | R88: 92600
A89: ORD1088 | B89: Apr | C89: 4 | D89: 2024-04-28 | E89: Kolkata | F89: Electronics | G89: Laptop | H89: Marketplace | I89: 3 | J89: 499 | K89: 1497 | L89: 15 | M89: 1272.45 | N89: 5 | O89: Delivered | P89: COD | R89: 1300
A90: ORD1089 | B90: May | C90: 5 | D90: 2024-05-10 | E90: Kolkata | F90: Home & Kitchen | G90: LED Bulb | H90: Mobile App | I90: 11 | J90: 4999 | K90: 54989 | L90: 20 | M90: 43991.2 | N90: 1 | O90: Delivered | P90: Credit Card | R90: 45700
A91: ORD1090 | B91: Jun | C91: 6 | D91: 2024-06-02 | E91: Kolkata | F91: Clothing | G91: T-Shirt | H91: Website | I91: 13 | J91: 24999 | K91: 324987 | L91: 0 | M91: 324987 | N91: 8 | O91: Delivered | P91: Debit Card | R91: 364300
A92: ORD1091 | B92: Jul | C92: 7 | D92: 2024-07-06 | E92: Hyderabad | F92: Home & Kitchen | G92: Mixer | H92: Mobile App | I92: 6 | J92: 2999 | K92: 17994 | L92: 5 | M92: 17094.3 | N92: 4 | O92: Delivered | P92: Net Banking | R92: 18000
A93: ORD1092 | B93: Aug | C93: 8 | D93: 2024-08-15 | E93: Delhi | F93: Clothing | G93: Jeans | H93: Marketplace | I93: 14 | J93: 2999 | K93: 41986 | L93: 20 | M93: 33588.8 | N93: 4 | O93: Delivered | P93: Net Banking | R93: 30000
A94: ORD1093 | B94: Sep | C94: 9 | D94: 2024-09-19 | E94: Hyderabad | F94: Home & Kitchen | G94: Iron | H94: Marketplace | I94: 1 | J94: 4999 | K94: 4999 | L94: 10 | M94: 4499.1 | N94: 9 | O94: Delivered | P94: COD | R94: 5100
A95: ORD1094 | B95: Oct | C95: 10 | D95: 2024-10-19 | E95: Hyderabad | F95: Home & Kitchen | G95: Iron | H95: Mobile App | I95: 14 | J95: 1499 | K95: 20986 | L95: 5 | M95: 19936.7 | N95: 7 | O95: Cancelled | P95: UPI | R95: 18400
A96: ORD1095 | B96: Nov | C96: 11 | D96: 2024-11-24 | E96: Hyderabad | F96: Home & Kitchen | G96: LED Bulb | H96: Marketplace | I96: 5 | J96: 299 | K96: 1495 | L96: 15 | M96: 1270.75 | N96: 5 | O96: Delivered | P96: UPI | R96: 1400
A97: ORD1096 | B97: Dec | C97: 12 | D97: 2024-12-21 | E97: Chennai | F97: Sports | G97: Badminton Racket | H97: Marketplace | I97: 13 | J97: 1999 | K97: 25987 | L97: 5 | M97: 24687.65 | N97: 4 | O97: Delivered | P97: Credit Card | R97: 25600
A98: ORD1097 | B98: Jan | C98: 1 | D98: 2024-01-06 | E98: Ahmedabad | F98: Electronics | G98: Earbuds | H98: Website | I98: 10 | J98: 1999 | K98: 19990 | L98: 5 | M98: 18990.5 | N98: 2 | O98: Cancelled | P98: Debit Card | R98: 20400
A99: ORD1098 | B99: Feb | C99: 2 | D99: 2024-02-10 | E99: Pune | F99: Clothing | G99: Jeans | H99: Marketplace | I99: 9 | J99: 1499 | K99: 13491 | L99: 5 | M99: 12816.45 | N99: 5 | O99: Cancelled | P99: COD | R99: 14600
... A108: ORD1107 | B108: Nov | C108: 11 | D108: 2024-11-12 | E108: Bangalore | F108: Electronics | G108: Earbuds | H108: Website | I108: 9 | J108: 1499 | K108: 13491 | L108: 5 | M108: 12816.45 | N108: 2 | O108: Delivered | P108: UPI | R108: 11400
A109: ORD1108 | B109: Dec | C109: 12 | D109: 2024-12-16 | E109: Pune | F109: Clothing | G109: Kurta | H109: Website | I109: 3 | J109: 1499 | K109: 4497 | L109: 0 | M109: 4497 | N109: 3 | O109: Returned | P109: Net Banking | Q109: Quality Issue | R109: 4800
A110: ORD1109 | B110: Jan | C110: 1 | D110: 2024-01-01 | E110: Delhi | F110: Sports | G110: Badminton Racket | H110: Mobile App | I110: 9 | J110: 999 | K110: 8991 | L110: 20 | M110: 7192.8 | N110: 1 | O110: Returned | P110: Net Banking | Q110: Changed Mind | R110: 7100
A111: ORD1110 | B111: Feb | C111: 2 | D111: 2024-02-05 | E111: Kolkata | F111: Electronics | G111: Smartwatch | H111: Mobile App | I111: 11 | J111: 499 | K111: 5489 | L111: 15 | M111: 4665.65 | N111: 8 | O111: Delivered | P111: UPI | R111: 4400
A112: ORD1111 | B112: Mar | C112: 3 | D112: 2024-03-15 | E112: Hyderabad | F112: Electronics | G112: Laptop | H112: Marketplace | I112: 11 | J112: 12999 | K112: 142989 | L112: 20 | M112: 114391.2 | N112: 6 | O112: Delivered | P112: Net Banking | R112: 115400
A113: ORD1112 | B113: Apr | C113: 4 | D113: 2024-04-27 | E113: Kolkata | F113: Books | G113: Biography | H113: Website | I113: 13 | J113: 499 | K113: 6487 | L113: 20 | M113: 5189.6 | N113: 4 | O113: Delivered | P113: Credit Card | R113: 5100
A114: ORD1113 | B114: May | C114: 5 | D114: 2024-05-22 | E114: Kolkata | F114: Sports | G114: Football | H114: Marketplace | I114: 2 | J114: 1999 | K114: 3998 | L114: 15 | M114: 3398.3 | N114: 6 | O114: Delivered | P114: Debit Card | R114: 3900
A115: ORD1114 | B115: Jun | C115: 6 | D115: 2024-06-18 | E115: Delhi | F115: Sports | G115: Cricket Bat | H115: Website | I115: 2 | J115: 2999 | K115: 5998 | L115: 0 | M115: 5998 | N115: 6 | O115: Returned | P115: Net Banking | Q115: Quality Issue | R115: 6200
A116: ORD1115 | B116: Jul | C116: 7 | D116: 2024-07-04 | E116: Delhi | F116: Books | G116: Textbook | H116: Mobile App | I116: 6 | J116: 24999 | K116: 149994 | L116: 15 | M116: 127494.9 | N116: 1 | O116: Pending | P116: Net Banking | R116: 120300
A117: ORD1116 | B117: Aug | C117: 8 | D117: 2024-08-25 | E117: Chennai | F117: Books | G117: Biography | H117: Website | I117: 11 | J117: 4999 | K117: 54989 | L117: 5 | M117: 52239.55 | N117: 2 | O117: Delivered | P117: Net Banking | R117: 50200
A118: ORD1117 | B118: Sep | C118: 9 | D118: 2024-09-22 | E118: Chennai | F118: Home & Kitchen | G118: LED Bulb | H118: Mobile App | I118: 14 | J118: 7999 | K118: 111986 | L118: 20 | M118: 89588.8 | N118: 10 | O118: Delivered | P118: Net Banking | R118: 76900
A119: ORD1118 | B119: Oct | C119: 10 | D119: 2024-10-13 | E119: Bangalore | F119: Home & Kitchen | G119: Mixer | H119: Mobile App | I119: 12 | J119: 1499 | K119: 17988 | L119: 10 | M119: 16189.2 | N119: 6 | O119: Delivered | P119: Credit Card | R119: 16500
...

Sheet Monthly_Summary
A1: Month | B1: Month_No | C1: Total_Orders | D1: Total_Revenue | E1: Total_Net_Revenue | F1: Target_Revenue | G1: Achievement_% | H1: Returns | I1: Return_Rate_% | J1: MoM_Growth_%
A2: Jan | B2: 1 | C2: =COUNTIFS(Raw_Data!B:B,A2) -> 25 | D2: =SUMIF(Raw_Data!B:B,A2,Raw_Data!K:K) -> 816327 | E2: =SUMIF(Raw_Data!B:B,A2,Raw_Data!M:M) -> 708897.35 | F2: =SUMIF(Raw_Data!B:B,A2,Raw_Data!R:R) -> 722400 | G2: =IFERROR(E2/F2,0) -> 0.98130862 | H2: =COUNTIFS(Raw_Data!B:B,A2,Raw_Data!O:O,"Returned") -> 6 | I2: =IFERROR(H2/C2,0) -> 0.24 | J2: 0
A3: Feb | B3: 2 | C3: =COUNTIFS(Raw_Data!B:B,A3) -> 25 | D3: =SUMIF(Raw_Data!B:B,A3,Raw_Data!K:K) -> 1244097 | E3: =SUMIF(Raw_Data!B:B,A3,Raw_Data!M:M) -> 1118868.6 | F3: =SUMIF(Raw_Data!B:B,A3,Raw_Data!R:R) -> 1140500 | G3: =IFERROR(E3/F3,0) -> 0.98103345 | H3: =COUNTIFS(Raw_Data!B:B,A3,Raw_Data!O:O,"Returned") -> 6 | I3: =IFERROR(H3/C3,0) -> 0.24 | J3: =IFERROR((E3-E2)/E2,0) -> 0.57832252
A4: Mar | B4: 3 | C4: =COUNTIFS(Raw_Data!B:B,A4) -> 25 | D4: =SUMIF(Raw_Data!B:B,A4,Raw_Data!K:K) -> 1767444 | E4: =SUMIF(Raw_Data!B:B,A4,Raw_Data!M:M) -> 1520021.9 | F4: =SUMIF(Raw_Data!B:B,A4,Raw_Data!R:R) -> 1427500 | G4: =IFERROR(E4/F4,0) -> 1.064814 | H4: =COUNTIFS(Raw_Data!B:B,A4,Raw_Data!O:O,"Returned") -> 0 | I4: =IFERROR(H4/C4,0) -> 0 | J4: =IFERROR((E4-E3)/E3,0) -> 0.35853476
A5: Apr | B5: 4 | C5: =COUNTIFS(Raw_Data!B:B,A5) -> 25 | D5: =SUMIF(Raw_Data!B:B,A5,Raw_Data!K:K) -> 1743268 | E5: =SUMIF(Raw_Data!B:B,A5,Raw_Data!M:M) -> 1560955.1 | F5: =SUMIF(Raw_Data!B:B,A5,Raw_Data!R:R) -> 1443900 | G5: =IFERROR(E5/F5,0) -> 1.0810687 | H5: =COUNTIFS(Raw_Data!B:B,A5,Raw_Data!O:O,"Returned") -> 3 | I5: =IFERROR(H5/C5,0) -> 0.12 | J5: =IFERROR((E5-E4)/E4,0) -> 0.026929282
A6: May | B6: 5 | C6: =COUNTIFS(Raw_Data!B:B,A6) -> 25 | D6: =SUMIF(Raw_Data!B:B,A6,Raw_Data!K:K) -> 847915 | E6: =SUMIF(Raw_Data!B:B,A6,Raw_Data!M:M) -> 791762.4 | F6: =SUMIF(Raw_Data!B:B,A6,Raw_Data!R:R) -> 756900 | G6: =IFERROR(E6/F6,0) -> 1.0460595 | H6: =COUNTIFS(Raw_Data!B:B,A6,Raw_Data!O:O,"Returned") -> 5 | I6: =IFERROR(H6/C6,0) -> 0.2 | J6: =IFERROR((E6-E5)/E5,0) -> -0.49277053
A7: Jun | B7: 6 | C7: =COUNTIFS(Raw_Data!B:B,A7) -> 25 | D7: =SUMIF(Raw_Data!B:B,A7,Raw_Data!K:K) -> 1652751 | E7: =SUMIF(Raw_Data!B:B,A7,Raw_Data!M:M) -> 1577165.6 | F7: =SUMIF(Raw_Data!B:B,A7,Raw_Data!R:R) -> 1543100 | G7: =IFERROR(E7/F7,0) -> 1.0220761 | H7: =COUNTIFS(Raw_Data!B:B,A7,Raw_Data!O:O,"Returned") -> 4 | I7: =IFERROR(H7/C7,0) -> 0.16 | J7: =IFERROR((E7-E6)/E6,0) -> 0.9919683
A8: Jul | B8: 7 | C8: =COUNTIFS(Raw_Data!B:B,A8) -> 25 | D8: =SUMIF(Raw_Data!B:B,A8,Raw_Data!K:K) -> 897139 | E8: =SUMIF(Raw_Data!B:B,A8,Raw_Data!M:M) -> 809349.15 | F8: =SUMIF(Raw_Data!B:B,A8,Raw_Data!R:R) -> 756000 | G8: =IFERROR(E8/F8,0) -> 1.0705677 | H8: =COUNTIFS(Raw_Data!B:B,A8,Raw_Data!O:O,"Returned") -> 3 | I8: =IFERROR(H8/C8,0) -> 0.12 | J8: =IFERROR((E8-E7)/E7,0) -> -0.48683312
A9: Aug | B9: 8 | C9: =COUNTIFS(Raw_Data!B:B,A9) -> 25 | D9: =SUMIF(Raw_Data!B:B,A9,Raw_Data!K:K) -> 1730857 | E9: =SUMIF(Raw_Data!B:B,A9,Raw_Data!M:M) -> 1562267 | F9: =SUMIF(Raw_Data!B:B,A9,Raw_Data!R:R) -> 1544000 | G9: =IFERROR(E9/F9,0) -> 1.011831 | H9: =COUNTIFS(Raw_Data!B:B,A9,Raw_Data!O:O,"Returned") -> 1 | I9: =IFERROR(H9/C9,0) -> 0.04 | J9: =IFERROR((E9-E8)/E8,0) -> 0.9302757
A10: Sep | B10: 9 | C10: =COUNTIFS(Raw_Data!B:B,A10) -> 25 | D10: =SUMIF(Raw_Data!B:B,A10,Raw_Data!K:K) -> 1795283 | E10: =SUMIF(Raw_Data!B:B,A10,Raw_Data!M:M) -> 1567008.7 | F10: =SUMIF(Raw_Data!B:B,A10,Raw_Data!R:R) -> 1487400 | G10: =IFERROR(E10/F10,0) -> 1.053522 | H10: =COUNTIFS(Raw_Data!B:B,A10,Raw_Data!O:O,"Returned") -> 6 | I10: =IFERROR(H10/C10,0) -> 0.24 | J10: =IFERROR((E10-E9)/E9,0) -> 0.0030351086
A11: Oct | B11: 10 | C11: =COUNTIFS(Raw_Data!B:B,A11) -> 25 | D11: =SUMIF(Raw_Data!B:B,A11,Raw_Data!K:K) -> 1626889 | E11: =SUMIF(Raw_Data!B:B,A11,Raw_Data!M:M) -> 1504139.1 | F11: =SUMIF(Raw_Data!B:B,A11,Raw_Data!R:R) -> 1557900 | G11: =IFERROR(E11/F11,0) -> 0.9654914 | H11: =COUNTIFS(Raw_Data!B:B,A11,Raw_Data!O:O,"Returned") -> 3 | I11: =IFERROR(H11/C11,0) -> 0.12 | J11: =IFERROR((E11-E10)/E10,0) -> -0.040120774
A12: Nov | B12: 11 | C12: =COUNTIFS(Raw_Data!B:B,A12) -> 25 | D12: =SUMIF(Raw_Data!B:B,A12,Raw_Data!K:K) -> 1039392 | E12: =SUMIF(Raw_Data!B:B,A12,Raw_Data!M:M) -> 905156.05 | F12: =SUMIF(Raw_Data!B:B,A12,Raw_Data!R:R) -> 893400 | G12: =IFERROR(E12/F12,0) -> 1.0131588 | H12: =COUNTIFS(Raw_Data!B:B,A12,Raw_Data!O:O,"Returned") -> 1 | I12: =IFERROR(H12/C12,0) -> 0.04 | J12: =IFERROR((E12-E11)/E11,0) -> -0.39822316
A13: Dec | B13: 12 | C13: =COUNTIFS(Raw_Data!B:B,A13) -> 25 | D13: =SUMIF(Raw_Data!B:B,A13,Raw_Data!K:K) -> 920349 | E13: =SUMIF(Raw_Data!B:B,A13,Raw_Data!M:M) -> 857765.2 | F13: =SUMIF(Raw_Data!B:B,A13,Raw_Data!R:R) -> 825200 | G13: =IFERROR(E13/F13,0) -> 1.0394634 | H13: =COUNTIFS(Raw_Data!B:B,A13,Raw_Data!O:O,"Returned") -> 6 | I13: =IFERROR(H13/C13,0) -> 0.24 | J13: =IFERROR((E13-E12)/E12,0) -> -0.052356552

Sheet City_Analysis
A1: City | B1: Total_Orders | C1: Total_Revenue | D1: Net_Revenue | E1: Returns | F1: Return_Rate_% | G1: Avg_Order_Value | H1: Rank
A2: Mumbai | B2: =COUNTIF(Raw_Data!E:E,A2) -> 38 | C2: =SUMIF(Raw_Data!E:E,A2,Raw_Data!K:K) -> 3195035 | D2: =SUMIF(Raw_Data!E:E,A2,Raw_Data!M:M) -> 2883388.1 | E2: =COUNTIFS(Raw_Data!E:E,A2,Raw_Data!O:O,"Returned") -> 5 | F2: =IFERROR(E2/B2,0) -> 0.13157895 | G2: =IFERROR(C2/B2,0) -> 84079.868 | H2: =RANK(C2,$C$2:$C$9,0) -> 1
A3: Pune | B3: =COUNTIF(Raw_Data!E:E,A3) -> 36 | C3: =SUMIF(Raw_Data!E:E,A3,Raw_Data!K:K) -> 2421021 | D3: =SUMIF(Raw_Data!E:E,A3,Raw_Data!M:M) -> 2193023.6 | E3: =COUNTIFS(Raw_Data!E:E,A3,Raw_Data!O:O,"Returned") -> 7 | F3: =IFERROR(E3/B3,0) -> 0.19444444 | G3: =IFERROR(C3/B3,0) -> 67250.583 | H3: =RANK(C3,$C$2:$C$9,0) -> 2
A4: Ahmedabad | B4: =COUNTIF(Raw_Data!E:E,A4) -> 38 | C4: =SUMIF(Raw_Data!E:E,A4,Raw_Data!K:K) -> 2389891 | D4: =SUMIF(Raw_Data!E:E,A4,Raw_Data!M:M) -> 2086856.6 | E4: =COUNTIFS(Raw_Data!E:E,A4,Raw_Data!O:O,"Returned") -> 6 | F4: =IFERROR(E4/B4,0) -> 0.15789474 | G4: =IFERROR(C4/B4,0) -> 62891.868 | H4: =RANK(C4,$C$2:$C$9,0) -> 3
A5: Hyderabad | B5: =COUNTIF(Raw_Data!E:E,A5) -> 39 | C5: =SUMIF(Raw_Data!E:E,A5,Raw_Data!K:K) -> 2120015 | D5: =SUMIF(Raw_Data!E:E,A5,Raw_Data!M:M) -> 1918994.8 | E5: =COUNTIFS(Raw_Data!E:E,A5,Raw_Data!O:O,"Returned") -> 3 | F5: =IFERROR(E5/B5,0) -> 0.076923077 | G5: =IFERROR(C5/B5,0) -> 54359.359 | H5: =RANK(C5,$C$2:$C$9,0) -> 4
A6: Kolkata | B6: =COUNTIF(Raw_Data!E:E,A6) -> 45 | C6: =SUMIF(Raw_Data!E:E,A6,Raw_Data!K:K) -> 1742653 | D6: =SUMIF(Raw_Data!E:E,A6,Raw_Data!M:M) -> 1634166.9 | E6: =COUNTIFS(Raw_Data!E:E,A6,Raw_Data!O:O,"Returned") -> 7 | F6: =IFERROR(E6/B6,0) -> 0.15555556 | G6: =IFERROR(C6/B6,0) -> 38725.622 | H6: =RANK(C6,$C$2:$C$9,0) -> 5
A7: Chennai | B7: =COUNTIF(Raw_Data!E:E,A7) -> 41 | C7: =SUMIF(Raw_Data!E:E,A7,Raw_Data!K:K) -> 1626283 | D7: =SUMIF(Raw_Data!E:E,A7,Raw_Data!M:M) -> 1513882.9 | E7: =COUNTIFS(Raw_Data!E:E,A7,Raw_Data!O:O,"Returned") -> 7 | F7: =IFERROR(E7/B7,0) -> 0.17073171 | G7: =IFERROR(C7/B7,0) -> 39665.439 | H7: =RANK(C7,$C$2:$C$9,0) -> 7
A8: Delhi | B8: =COUNTIF(Raw_Data!E:E,A8) -> 30 | C8: =SUMIF(Raw_Data!E:E,A8,Raw_Data!K:K) -> 1707660 | D8: =SUMIF(Raw_Data!E:E,A8,Raw_Data!M:M) -> 1491462.4 | E8: =COUNTIFS(Raw_Data!E:E,A8,Raw_Data!O:O,"Returned") -> 5 | F8: =IFERROR(E8/B8,0) -> 0.16666667 | G8: =IFERROR(C8/B8,0) -> 56922 | H8: =RANK(C8,$C$2:$C$9,0) -> 6
A9: Bangalore | B9: =COUNTIF(Raw_Data!E:E,A9) -> 33 | C9: =SUMIF(Raw_Data!E:E,A9,Raw_Data!K:K) -> 879153 | D9: =SUMIF(Raw_Data!E:E,A9,Raw_Data!M:M) -> 761580.85 | E9: =COUNTIFS(Raw_Data!E:E,A9,Raw_Data!O:O,"Returned") -> 4 | F9: =IFERROR(E9/B9,0) -> 0.12121212 | G9: =IFERROR(C9/B9,0) -> 26641 | H9: =RANK(C9,$C$2:$C$9,0) -> 8

Sheet Category_Performance
A1: Category | B1: Total_Orders | C1: Revenue | D1: Net_Revenue | E1: Units_Sold | F1: Avg_Unit_Price | G1: Revenue_Share_% | H1: Return_Rate_% | I1: Best_Channel
A2: Electronics | B2: =COUNTIF(Raw_Data!F:F,A2) -> 56 | C2: =SUMIF(Raw_Data!F:F,A2,Raw_Data!K:K) -> 4036928 | D2: =SUMIF(Raw_Data!F:F,A2,Raw_Data!M:M) -> 3636484.4 | E2: =SUMIF(Raw_Data!F:F,A2,Raw_Data!I:I) -> 472 | F2: =IFERROR(C2/B2,0) -> 72088 | G2: =IFERROR(C2/SUM($C$2:$C$6),0) -> 0.25102603 | H2: =IFERROR(COUNTIFS(Raw_Data!F:F,A2,Raw_Data!O:O,"Returned")/B2,0) -> 0.16071429 | I2: =IFERROR(INDEX(Raw_Data!H:H,MATCH(_xludf.maxifs(Raw_Data!K:K,Raw_Data!F:F,A2),Raw_Data!K:K,0)),"N/A") -> N/A
A3: Home & Kitchen | B3: =COUNTIF(Raw_Data!F:F,A3) -> 68 | C3: =SUMIF(Raw_Data!F:F,A3,Raw_Data!K:K) -> 3512072 | D3: =SUMIF(Raw_Data!F:F,A3,Raw_Data!M:M) -> 3221897.6 | E3: =SUMIF(Raw_Data!F:F,A3,Raw_Data!I:I) -> 528 | F3: =IFERROR(C3/B3,0) -> 51648.118 | G3: =IFERROR(C3/SUM($C$2:$C$6),0) -> 0.2183892 | H3: =IFERROR(COUNTIFS(Raw_Data!F:F,A3,Raw_Data!O:O,"Returned")/B3,0) -> 0.14705882 | I3: =IFERROR(INDEX(Raw_Data!H:H,MATCH(_xludf.maxifs(Raw_Data!K:K,Raw_Data!F:F,A3),Raw_Data!K:K,0)),"N/A") -> N/A
A4: Books | B4: =COUNTIF(Raw_Data!F:F,A4) -> 55 | C4: =SUMIF(Raw_Data!F:F,A4,Raw_Data!K:K) -> 3338567 | D4: =SUMIF(Raw_Data!F:F,A4,Raw_Data!M:M) -> 2975591.2 | E4: =SUMIF(Raw_Data!F:F,A4,Raw_Data!I:I) -> 433 | F4: =IFERROR(C4/B4,0) -> 60701.218 | G4: =IFERROR(C4/SUM($C$2:$C$6),0) -> 0.20760024 | H4: =IFERROR(COUNTIFS(Raw_Data!F:F,A4,Raw_Data!O:O,"Returned")/B4,0) -> 0.12727273 | I4: =IFERROR(INDEX(Raw_Data!H:H,MATCH(_xludf.maxifs(Raw_Data!K:K,Raw_Data!F:F,A4),Raw_Data!K:K,0)),"N/A") -> N/A
A5: Clothing | B5: =COUNTIF(Raw_Data!F:F,A5) -> 59 | C5: =SUMIF(Raw_Data!F:F,A5,Raw_Data!K:K) -> 3022820 | D5: =SUMIF(Raw_Data!F:F,A5,Raw_Data!M:M) -> 2668666.7 | E5: =SUMIF(Raw_Data!F:F,A5,Raw_Data!I:I) -> 480 | F5: =IFERROR(C5/B5,0) -> 51234.237 | G5: =IFERROR(C5/SUM($C$2:$C$6),0) -> 0.18796632 | H5: =IFERROR(COUNTIFS(Raw_Data!F:F,A5,Raw_Data!O:O,"Returned")/B5,0) -> 0.10169492 | I5: =IFERROR(INDEX(Raw_Data!H:H,MATCH(_xludf.maxifs(Raw_Data!K:K,Raw_Data!F:F,A5),Raw_Data!K:K,0)),"N/A") -> N/A
A6: Sports | B6: =COUNTIF(Raw_Data!F:F,A6) -> 62 | C6: =SUMIF(Raw_Data!F:F,A6,Raw_Data!K:K) -> 2171324 | D6: =SUMIF(Raw_Data!F:F,A6,Raw_Data!M:M) -> 1980716.1 | E6: =SUMIF(Raw_Data!F:F,A6,Raw_Data!I:I) -> 476 | F6: =IFERROR(C6/B6,0) -> 35021.355 | G6: =IFERROR(C6/SUM($C$2:$C$6),0) -> 0.13501822 | H6: =IFERROR(COUNTIFS(Raw_Data!F:F,A6,Raw_Data!O:O,"Returned")/B6,0) -> 0.19354839 | I6: =IFERROR(INDEX(Raw_Data!H:H,MATCH(_xludf.maxifs(Raw_Data!K:K,Raw_Data!F:F,A6),Raw_Data!K:K,0)),"N/A") -> N/A

Sheet Channel_Analysis
A1: Channel | B1: Total_Orders | C1: Revenue | D1: Net_Revenue | E1: Returns | F1: Return_Rate_% | G1: Revenue_Share_% | H1: Avg_Discount_%
A2: Website | B2: =COUNTIF(Raw_Data!H:H,A2) -> 100 | C2: =SUMIF(Raw_Data!H:H,A2,Raw_Data!K:K) -> 5437745 | D2: =SUMIF(Raw_Data!H:H,A2,Raw_Data!M:M) -> 4959581.6 | E2: =COUNTIFS(Raw_Data!H:H,A2,Raw_Data!O:O,"Returned") -> 16 | F2: =IFERROR(E2/B2,0) -> 0.16 | G2: =IFERROR(C2/SUM($C$2:$C$4),0) -> 0.33813224 | H2: =IFERROR(AVERAGEIF(Raw_Data!H:H,A2,Raw_Data!L:L)/100,0) -> 0.101
A3: Mobile App | B3: =COUNTIF(Raw_Data!H:H,A3) -> 108 | C3: =SUMIF(Raw_Data!H:H,A3,Raw_Data!K:K) -> 5500474 | D3: =SUMIF(Raw_Data!H:H,A3,Raw_Data!M:M) -> 4801475.9 | E3: =COUNTIFS(Raw_Data!H:H,A3,Raw_Data!O:O,"Returned") -> 16 | F3: =IFERROR(E3/B3,0) -> 0.14814815 | G3: =IFERROR(C3/SUM($C$2:$C$4),0) -> 0.34203288 | H3: =IFERROR(AVERAGEIF(Raw_Data!H:H,A3,Raw_Data!L:L)/100,0) -> 0.10833333
A4: Marketplace | B4: =COUNTIF(Raw_Data!H:H,A4) -> 92 | C4: =SUMIF(Raw_Data!H:H,A4,Raw_Data!K:K) -> 5143492 | D4: =SUMIF(Raw_Data!H:H,A4,Raw_Data!M:M) -> 4722298.6 | E4: =COUNTIFS(Raw_Data!H:H,A4,Raw_Data!O:O,"Returned") -> 12 | F4: =IFERROR(E4/B4,0) -> 0.13043478 | G4: =IFERROR(C4/SUM($C$2:$C$4),0) -> 0.31983487 | H4: =IFERROR(AVERAGEIF(Raw_Data!H:H,A4,Raw_Data!L:L)/100,0) -> 0.094565217

Sheet Return_Analysis
A1: RETURN ANALYSIS — FY2024
A3: Return Reason | B3: Count | C3: % of Returns
A4: Quality Issue | B4: =COUNTIF(Raw_Data!Q:Q,A4) -> 7 | C4: =IFERROR(B4/SUM($B$4:$B$8),0) -> 0.17073171
A5: Wrong Item | B5: =COUNTIF(Raw_Data!Q:Q,A5) -> 9 | C5: =IFERROR(B5/SUM($B$4:$B$8),0) -> 0.2195122
A6: Changed Mind | B6: =COUNTIF(Raw_Data!Q:Q,A6) -> 6 | C6: =IFERROR(B6/SUM($B$4:$B$8),0) -> 0.14634146
A7: Damaged | B7: =COUNTIF(Raw_Data!Q:Q,A7) -> 11 | C7: =IFERROR(B7/SUM($B$4:$B$8),0) -> 0.26829268
A8: Late Delivery | B8: =COUNTIF(Raw_Data!Q:Q,A8) -> 8 | C8: =IFERROR(B8/SUM($B$4:$B$8),0) -> 0.19512195
A11: Category | B11: Returns | C11: Return Rate %
A12: Electronics | B12: =COUNTIFS(Raw_Data!F:F,A12,Raw_Data!O:O,"Returned") -> 9 | C12: =IFERROR(B12/COUNTIF(Raw_Data!F:F,A12),0) -> 0.16071429
A13: Clothing | B13: =COUNTIFS(Raw_Data!F:F,A13,Raw_Data!O:O,"Returned") -> 6 | C13: =IFERROR(B13/COUNTIF(Raw_Data!F:F,A13),0) -> 0.10169492
A14: Home & Kitchen | B14: =COUNTIFS(Raw_Data!F:F,A14,Raw_Data!O:O,"Returned") -> 10 | C14: =IFERROR(B14/COUNTIF(Raw_Data!F:F,A14),0) -> 0.14705882
A15: Sports | B15: =COUNTIFS(Raw_Data!F:F,A15,Raw_Data!O:O,"Returned") -> 12 | C15: =IFERROR(B15/COUNTIF(Raw_Data!F:F,A15),0) -> 0.19354839
A16: Books | B16: =COUNTIFS(Raw_Data!F:F,A16,Raw_Data!O:O,"Returned") -> 7 | C16: =IFERROR(B16/COUNTIF(Raw_Data!F:F,A16),0) -> 0.12727273

Sheet MIS_Dashboard
A1: 🛒 E-COMMERCE ORDER & RETURNS DASHBOARD — FY2024
B3: Total Orders | C3: Total Revenue | E3: Net Revenue | F3: Return Rate % | H3: Avg Order Value | I3: Target Achv %
B4: =COUNTA(Raw_Data!A:A)-1 -> 300 | C4: =SUM(Raw_Data!K:K) -> 16081711 | E4: =SUM(Raw_Data!M:M) -> 14483356 | F4: =COUNTIF(Raw_Data!O:O,"Returned")/(COUNTA(Raw_Data!A:A)-1) -> 0.14666667 | H4: =SUM(Raw_Data!M:M)/(COUNTA(Raw_Data!A:A)-1) -> 48277.854 | I4: =SUM(Raw_Data!M:M)/SUM(Raw_Data!R:R) -> 1.0273195
A7: Monthly Performance Summary
A8: Month | B8: Orders | C8: Revenue | D8: Net Revenue | E8: Target | F8: Achievement % | G8: Returns | H8: Return Rate | I8: MoM Growth
A9: Jan | B9: =COUNTIF(Raw_Data!B:B,A9) -> 25 | C9: =SUMIF(Raw_Data!B:B,A9,Raw_Data!K:K) -> 816327 | D9: =SUMIF(Raw_Data!B:B,A9,Raw_Data!M:M) -> 708897.35 | E9: =SUMIF(Raw_Data!B:B,A9,Raw_Data!R:R) -> 722400 | F9: =IFERROR(D9/E9,0) -> 0.98130862 | G9: =COUNTIFS(Raw_Data!B:B,A9,Raw_Data!O:O,"Returned") -> 6 | H9: =IFERROR(G9/B9,0) -> 0.24 | I9: 0
A10: Feb | B10: =COUNTIF(Raw_Data!B:B,A10) -> 25 | C10: =SUMIF(Raw_Data!B:B,A10,Raw_Data!K:K) -> 1244097 | D10: =SUMIF(Raw_Data!B:B,A10,Raw_Data!M:M) -> 1118868.6 | E10: =SUMIF(Raw_Data!B:B,A10,Raw_Data!R:R) -> 1140500 | F10: =IFERROR(D10/E10,0) -> 0.98103345 | G10: =COUNTIFS(Raw_Data!B:B,A10,Raw_Data!O:O,"Returned") -> 6 | H10: =IFERROR(G10/B10,0) -> 0.24 | I10: =IFERROR((D10-D9)/D9,0) -> 0.57832252
A11: Mar | B11: =COUNTIF(Raw_Data!B:B,A11) -> 25 | C11: =SUMIF(Raw_Data!B:B,A11,Raw_Data!K:K) -> 1767444 | D11: =SUMIF(Raw_Data!B:B,A11,Raw_Data!M:M) -> 1520021.9 | E11: =SUMIF(Raw_Data!B:B,A11,Raw_Data!R:R) -> 1427500 | F11: =IFERROR(D11/E11,0) -> 1.064814 | G11: =COUNTIFS(Raw_Data!B:B,A11,Raw_Data!O:O,"Returned") -> 0 | H11: =IFERROR(G11/B11,0) -> 0 | I11: =IFERROR((D11-D10)/D10,0) -> 0.35853476
A12: Apr | B12: =COUNTIF(Raw_Data!B:B,A12) -> 25 | C12: =SUMIF(Raw_Data!B:B,A12,Raw_Data!K:K) -> 1743268 | D12: =SUMIF(Raw_Data!B:B,A12,Raw_Data!M:M) -> 1560955.1 | E12: =SUMIF(Raw_Data!B:B,A12,Raw_Data!R:R) -> 1443900 | F12: =IFERROR(D12/E12,0) -> 1.0810687 | G12: =COUNTIFS(Raw_Data!B:B,A12,Raw_Data!O:O,"Returned") -> 3 | H12: =IFERROR(G12/B12,0) -> 0.12 | I12: =IFERROR((D12-D11)/D11,0) -> 0.026929282
A13: May | B13: =COUNTIF(Raw_Data!B:B,A13) -> 25 | C13: =SUMIF(Raw_Data!B:B,A13,Raw_Data!K:K) -> 847915 | D13: =SUMIF(Raw_Data!B:B,A13,Raw_Data!M:M) -> 791762.4 | E13: =SUMIF(Raw_Data!B:B,A13,Raw_Data!R:R) -> 756900 | F13: =IFERROR(D13/E13,0) -> 1.0460595 | G13: =COUNTIFS(Raw_Data!B:B,A13,Raw_Data!O:O,"Returned") -> 5 | H13: =IFERROR(G13/B13,0) -> 0.2 | I13: =IFERROR((D13-D12)/D12,0) -> -0.49277053
A14: Jun | B14: =COUNTIF(Raw_Data!B:B,A14) -> 25 | C14: =SUMIF(Raw_Data!B:B,A14,Raw_Data!K:K) -> 1652751 | D14: =SUMIF(Raw_Data!B:B,A14,Raw_Data!M:M) -> 1577165.6 | E14: =SUMIF(Raw_Data!B:B,A14,Raw_Data!R:R) -> 1543100 | F14: =IFERROR(D14/E14,0) -> 1.0220761 | G14: =COUNTIFS(Raw_Data!B:B,A14,Raw_Data!O:O,"Returned") -> 4 | H14: =IFERROR(G14/B14,0) -> 0.16 | I14: =IFERROR((D14-D13)/D13,0) -> 0.9919683
A15: Jul | B15: =COUNTIF(Raw_Data!B:B,A15) -> 25 | C15: =SUMIF(Raw_Data!B:B,A15,Raw_Data!K:K) -> 897139 | D15: =SUMIF(Raw_Data!B:B,A15,Raw_Data!M:M) -> 809349.15 | E15: =SUMIF(Raw_Data!B:B,A15,Raw_Data!R:R) -> 756000 | F15: =IFERROR(D15/E15,0) -> 1.0705677 | G15: =COUNTIFS(Raw_Data!B:B,A15,Raw_Data!O:O,"Returned") -> 3 | H15: =IFERROR(G15/B15,0) -> 0.12 | I15: =IFERROR((D15-D14)/D14,0) -> -0.48683312
A16: Aug | B16: =COUNTIF(Raw_Data!B:B,A16) -> 25 | C16: =SUMIF(Raw_Data!B:B,A16,Raw_Data!K:K) -> 1730857 | D16: =SUMIF(Raw_Data!B:B,A16,Raw_Data!M:M) -> 1562267 | E16: =SUMIF(Raw_Data!B:B,A16,Raw_Data!R:R) -> 1544000 | F16: =IFERROR(D16/E16,0) -> 1.011831 | G16: =COUNTIFS(Raw_Data!B:B,A16,Raw_Data!O:O,"Returned") -> 1 | H16: =IFERROR(G16/B16,0) -> 0.04 | I16: =IFERROR((D16-D15)/D15,0) -> 0.9302757
A17: Sep | B17: =COUNTIF(Raw_Data!B:B,A17) -> 25 | C17: =SUMIF(Raw_Data!B:B,A17,Raw_Data!K:K) -> 1795283 | D17: =SUMIF(Raw_Data!B:B,A17,Raw_Data!M:M) -> 1567008.7 | E17: =SUMIF(Raw_Data!B:B,A17,Raw_Data!R:R) -> 1487400 | F17: =IFERROR(D17/E17,0) -> 1.053522 | G17: =COUNTIFS(Raw_Data!B:B,A17,Raw_Data!O:O,"Returned") -> 6 | H17: =IFERROR(G17/B17,0) -> 0.24 | I17: =IFERROR((D17-D16)/D16,0) -> 0.0030351086
A18: Oct | B18: =COUNTIF(Raw_Data!B:B,A18) -> 25 | C18: =SUMIF(Raw_Data!B:B,A18,Raw_Data!K:K) -> 1626889 | D18: =SUMIF(Raw_Data!B:B,A18,Raw_Data!M:M) -> 1504139.1 | E18: =SUMIF(Raw_Data!B:B,A18,Raw_Data!R:R) -> 1557900 | F18: =IFERROR(D18/E18,0) -> 0.9654914 | G18: =COUNTIFS(Raw_Data!B:B,A18,Raw_Data!O:O,"Returned") -> 3 | H18: =IFERROR(G18/B18,0) -> 0.12 | I18: =IFERROR((D18-D17)/D17,0) -> -0.040120774
A19: Nov | B19: =COUNTIF(Raw_Data!B:B,A19) -> 25 | C19: =SUMIF(Raw_Data!B:B,A19,Raw_Data!K:K) -> 1039392 | D19: =SUMIF(Raw_Data!B:B,A19,Raw_Data!M:M) -> 905156.05 | E19: =SUMIF(Raw_Data!B:B,A19,Raw_Data!R:R) -> 893400 | F19: =IFERROR(D19/E19,0) -> 1.0131588 | G19: =COUNTIFS(Raw_Data!B:B,A19,Raw_Data!O:O,"Returned") -> 1 | H19: =IFERROR(G19/B19,0) -> 0.04 | I19: =IFERROR((D19-D18)/D18,0) -> -0.39822316
A20: Dec | B20: =COUNTIF(Raw_Data!B:B,A20) -> 25 | C20: =SUMIF(Raw_Data!B:B,A20,Raw_Data!K:K) -> 920349 | D20: =SUMIF(Raw_Data!B:B,A20,Raw_Data!M:M) -> 857765.2 | E20: =SUMIF(Raw_Data!B:B,A20,Raw_Data!R:R) -> 825200 | F20: =IFERROR(D20/E20,0) -> 1.0394634 | G20: =COUNTIFS(Raw_Data!B:B,A20,Raw_Data!O:O,"Returned") -> 6 | H20: =IFERROR(G20/B20,0) -> 0.24 | I20: =IFERROR((D20-D19)/D19,0) -> -0.052356552
